bigmathutils/__init__.py
bigmathutils/big.py
bigmathutils-0.0.1.dist-info/licenses/LICENSE
bigmathutils-0.0.1.dist-info/METADATA
bigmathutils-0.0.1.dist-info/WHEEL
bigmathutils-0.0.1.dist-info/top_level.txt
bigmathutils-0.0.1.dist-info/RECORD
