Metadata-Version: 2.4
Name: bigmathutils
Version: 0.0.1
Summary: A small, easy-to-use wrapper around Python's Decimal with configurable precision and rounding.
Author: Matt
License: MIT
Project-URL: Homepage, https://github.com/mariaboyd12/bigmathutils
Project-URL: Source, https://github.com/mariaboyd12/bigmathutils
Project-URL: Issues, https://github.com/mariaboyd12/bigmathutils/issues
Requires-Python: >=3.7
License-File: LICENSE
Provides-Extra: dev
Requires-Dist: pytest; extra == "dev"
Requires-Dist: build; extra == "dev"
Requires-Dist: twine; extra == "dev"
Dynamic: license-file
